dnn_tts_torch/__init__.py
dnn_tts_torch/audio.py
dnn_tts_torch/dl_and_preprop_dataset.py
dnn_tts_torch/hparams.py
dnn_tts_torch/logger.py
dnn_tts_torch/metrics_calc.py
dnn_tts_torch/synthesize.py
dnn_tts_torch/test.py
dnn_tts_torch/train-ssrn.py
dnn_tts_torch/train-text2mel.py
dnn_tts_torch/utils.py
dnn_tts_torch/datasets/__init__.py
dnn_tts_torch/datasets/data_loader.py
dnn_tts_torch/datasets/lj_speech.py
dnn_tts_torch/datasets/ru_speech.py
dnn_tts_torch/models/__init__.py
dnn_tts_torch/models/layers.py
dnn_tts_torch/models/ssrn.py
dnn_tts_torch/models/text2mel.py
dnn_tts_torch-0.0.9.dist-info/METADATA
dnn_tts_torch-0.0.9.dist-info/WHEEL
dnn_tts_torch-0.0.9.dist-info/top_level.txt
dnn_tts_torch-0.0.9.dist-info/RECORD
